{"expireTime":9007200842154215000,"key":"transformer-remark-markdown-ast-0cadbe087b636e8adb8b1a088fe73aca-gatsby-remark-imagesgatsby-remark-responsive-iframegatsby-remark-prismjsgatsby-remark-copy-linked-filesgatsby-remark-smartypants-","val":{"type":"root","children":[{"type":"paragraph","children":[{"type":"text","value":"This article is a part of a series where I go through ","position":{"start":{"line":1,"column":1,"offset":0},"end":{"line":1,"column":55,"offset":54},"indent":[]}},{"type":"link","title":null,"url":"https://teachyourselfcs.com/","children":[{"type":"text","value":"teachyourselfcs","position":{"start":{"line":1,"column":56,"offset":55},"end":{"line":1,"column":71,"offset":70},"indent":[]}}],"position":{"start":{"line":1,"column":55,"offset":54},"end":{"line":1,"column":102,"offset":101},"indent":[]}},{"type":"text","value":".\nIf you would like to start at the beginning start ","position":{"start":{"line":1,"column":102,"offset":101},"end":{"line":2,"column":51,"offset":153},"indent":[1]}},{"type":"link","title":null,"url":"http://localhost:8000/teachyourselfcs/programming/00:getting-started/","children":[{"type":"text","value":"here","position":{"start":{"line":2,"column":52,"offset":154},"end":{"line":2,"column":56,"offset":158},"indent":[]}}],"position":{"start":{"line":2,"column":51,"offset":153},"end":{"line":2,"column":128,"offset":230},"indent":[]}},{"type":"text","value":".","position":{"start":{"line":2,"column":128,"offset":230},"end":{"line":2,"column":129,"offset":231},"indent":[]}}],"position":{"start":{"line":1,"column":1,"offset":0},"end":{"line":2,"column":129,"offset":231},"indent":[1]}},{"type":"heading","depth":5,"children":[{"type":"text","value":"INTRO","position":{"start":{"line":4,"column":7,"offset":239},"end":{"line":4,"column":12,"offset":244},"indent":[]}}],"position":{"start":{"line":4,"column":1,"offset":233},"end":{"line":4,"column":12,"offset":244},"indent":[]}},{"type":"heading","depth":5,"children":[{"type":"text","value":"LECTURE","position":{"start":{"line":5,"column":7,"offset":251},"end":{"line":5,"column":14,"offset":258},"indent":[]}}],"position":{"start":{"line":5,"column":1,"offset":245},"end":{"line":5,"column":14,"offset":258},"indent":[]}},{"type":"heading","depth":6,"children":[{"type":"text","value":"L01","position":{"start":{"line":6,"column":8,"offset":266},"end":{"line":6,"column":11,"offset":269},"indent":[]}}],"position":{"start":{"line":6,"column":1,"offset":259},"end":{"line":6,"column":11,"offset":269},"indent":[]}},{"type":"paragraph","children":[{"type":"text","value":"Class starts by going over some sytax for Scheme.languages do mathmatical operations the same way we learned in grade school:\n","position":{"start":{"line":7,"column":1,"offset":270},"end":{"line":8,"column":1,"offset":396},"indent":[1]}},{"type":"html","value":"<br>","position":{"start":{"line":8,"column":1,"offset":396},"end":{"line":8,"column":5,"offset":400},"indent":[]}},{"type":"html","value":"<code class=\"language-text\">2 + 2 + 3</code>","position":{"start":{"line":8,"column":5,"offset":400},"end":{"line":8,"column":16,"offset":411},"indent":[]}},{"type":"html","value":"<br>","position":{"start":{"line":8,"column":16,"offset":411},"end":{"line":8,"column":20,"offset":415},"indent":[]}},{"type":"text","value":" \nScheme uses a different syntax where operator is the always on the left and you can as many numbers as you would like: \n","position":{"start":{"line":8,"column":20,"offset":415},"end":{"line":10,"column":1,"offset":537},"indent":[1,1]}},{"type":"html","value":"<br>","position":{"start":{"line":10,"column":1,"offset":537},"end":{"line":10,"column":5,"offset":541},"indent":[]}},{"type":"html","value":"<code class=\"language-text\">(+ 2 2 3)</code>","position":{"start":{"line":10,"column":5,"offset":541},"end":{"line":10,"column":16,"offset":552},"indent":[]}},{"type":"html","value":"<br>","position":{"start":{"line":10,"column":16,"offset":552},"end":{"line":10,"column":20,"offset":556},"indent":[]}},{"type":"text","value":"\nNow lets say we want to do something like:","position":{"start":{"line":10,"column":20,"offset":556},"end":{"line":11,"column":43,"offset":599},"indent":[1]}},{"type":"break","position":{"start":{"line":11,"column":43,"offset":599},"end":{"line":12,"column":1,"offset":602},"indent":[1]}},{"type":"html","value":"<br>","position":{"start":{"line":12,"column":1,"offset":602},"end":{"line":12,"column":5,"offset":606},"indent":[]}},{"type":"html","value":"<code class=\"language-text\">2 + 2 +  3 - 4</code>","position":{"start":{"line":12,"column":5,"offset":606},"end":{"line":12,"column":21,"offset":622},"indent":[]}},{"type":"html","value":"<br>","position":{"start":{"line":12,"column":21,"offset":622},"end":{"line":12,"column":25,"offset":626},"indent":[]}},{"type":"text","value":"\nIn Scheme you can simply nest operators: \n","position":{"start":{"line":12,"column":25,"offset":626},"end":{"line":14,"column":1,"offset":669},"indent":[1,1]}},{"type":"html","value":"<br>","position":{"start":{"line":14,"column":1,"offset":669},"end":{"line":14,"column":5,"offset":673},"indent":[]}},{"type":"html","value":"<code class=\"language-text\">(- (+ 2 2 3) 4)</code>","position":{"start":{"line":14,"column":5,"offset":673},"end":{"line":14,"column":22,"offset":690},"indent":[]}},{"type":"html","value":"<br>","position":{"start":{"line":14,"column":22,"offset":690},"end":{"line":14,"column":26,"offset":694},"indent":[]}}],"position":{"start":{"line":7,"column":1,"offset":270},"end":{"line":14,"column":26,"offset":694},"indent":[1,1,1,1,1,1,1]}},{"type":"paragraph","children":[{"type":"text","value":"Scheme will ","position":{"start":{"line":16,"column":1,"offset":696},"end":{"line":16,"column":13,"offset":708},"indent":[]}}],"position":{"start":{"line":16,"column":1,"offset":696},"end":{"line":16,"column":13,"offset":708},"indent":[]}},{"type":"heading","depth":6,"children":[{"type":"text","value":"L02","position":{"start":{"line":17,"column":8,"offset":716},"end":{"line":17,"column":11,"offset":719},"indent":[]}}],"position":{"start":{"line":17,"column":1,"offset":709},"end":{"line":17,"column":11,"offset":719},"indent":[]}},{"type":"heading","depth":5,"children":[{"type":"text","value":"BOOK","position":{"start":{"line":18,"column":7,"offset":726},"end":{"line":18,"column":11,"offset":730},"indent":[]}}],"position":{"start":{"line":18,"column":1,"offset":720},"end":{"line":18,"column":11,"offset":730},"indent":[]}},{"type":"heading","depth":6,"children":[{"type":"text","value":"1.1","position":{"start":{"line":19,"column":8,"offset":738},"end":{"line":19,"column":11,"offset":741},"indent":[]}}],"position":{"start":{"line":19,"column":1,"offset":731},"end":{"line":19,"column":11,"offset":741},"indent":[]}},{"type":"heading","depth":6,"children":[{"type":"text","value":"1.2","position":{"start":{"line":20,"column":8,"offset":749},"end":{"line":20,"column":11,"offset":752},"indent":[]}}],"position":{"start":{"line":20,"column":1,"offset":742},"end":{"line":20,"column":11,"offset":752},"indent":[]}},{"type":"heading","depth":6,"children":[{"type":"text","value":"1.3","position":{"start":{"line":21,"column":8,"offset":760},"end":{"line":21,"column":11,"offset":763},"indent":[]}}],"position":{"start":{"line":21,"column":1,"offset":753},"end":{"line":21,"column":11,"offset":763},"indent":[]}},{"type":"heading","depth":5,"children":[{"type":"text","value":"LABS","position":{"start":{"line":22,"column":7,"offset":770},"end":{"line":22,"column":11,"offset":774},"indent":[]}}],"position":{"start":{"line":22,"column":1,"offset":764},"end":{"line":22,"column":11,"offset":774},"indent":[]}},{"type":"heading","depth":6,"children":[{"type":"text","value":"Lab 1","position":{"start":{"line":23,"column":8,"offset":782},"end":{"line":23,"column":13,"offset":787},"indent":[]}}],"position":{"start":{"line":23,"column":1,"offset":775},"end":{"line":23,"column":14,"offset":788},"indent":[]}},{"type":"heading","depth":6,"children":[{"type":"text","value":"Lab 2","position":{"start":{"line":24,"column":8,"offset":796},"end":{"line":24,"column":13,"offset":801},"indent":[]}}],"position":{"start":{"line":24,"column":1,"offset":789},"end":{"line":24,"column":14,"offset":802},"indent":[]}}],"position":{"start":{"line":1,"column":1,"offset":0},"end":{"line":24,"column":14,"offset":802}}}}